{"input_1": {"id": "input_1", "name": "Input 1", "type": "Input", "pos": {"x": 345, "y": 39}, "connections": {"inbound": [], "outbound": ["conv2d_1"]}, "arguments": {"shape": {"value": "( 28, 28, 1 )", "type": "text", "render": "text"}, "batch_size": {"value": "None", "type": "number", "render": "text"}, "name": {"value": "None", "type": "text", "render": "text"}, "dtype": {"value": "None", "type": "text", "render": "text"}, "sparse": {"value": "False", "type": "list", "render": "list", "options": [{"name": "True", "value": "True"}, {"name": "False", "value": "False"}]}, "tensor": {"value": "None", "type": "text", "render": false}, "ragged": {"value": "False", "type": "list", "render": "list", "options": [{"name": "True", "value": "True"}, {"name": "False", "value": "False"}]}}}, "conv2d_1": {"id": "conv2d_1", "name": "Conv2D 1", "type": "Conv2D", "pos": {"x": 356, "y": 161}, "connections": {"inbound": ["input_1"], "outbound": ["conv2d_2"]}, "arguments": {"filters": {"value": "32", "type": "number", "render": "text"}, "kernel_size": {"value": "3", "type": "number", "render": "text"}, "strides": {"value": "2", "type": "number", "render": "text"}, "padding": {"value": "same", "type": "list", "render": "list", "options": [{"name": "valid", "value": "'valid'"}, {"name": "same", "value": "'same'"}]}, "activation": {"value": "relu", "type": "text", "render": "list", "options": [{"name": "None", "value": "None"}, {"name": "relu", "value": "\"relu\""}, {"name": "sigmoid", "value": "\"sigmoid\""}, {"name": "softmax", "value": "\"softmax\""}, {"name": "swish", "value": "\"swish\""}, {"name": "tanh", "value": "\"tanh\""}]}, "use_bias": {"value": "True", "type": "list", "render": "list", "options": [{"name": "True", "value": "True"}, {"name": "False", "value": "False"}]}, "kernel_initializer": {"value": "glorot_uniform", "type": "list", "render": "list", "options": [{"name": "glorot_uniform", "value": "'glorot_uniform'"}, {"name": "glorot_normal", "value": "'glorot_normal'"}, {"name": "he_normal", "value": "'he_normal'"}, {"name": "he_uniform", "value": "'he_uniform'"}, {"name": "identity", "value": "'identity'"}, {"name": "lecun_normal", "value": "'lecun_normal'"}, {"name": "lecun_uniform", "value": "'lecun_uniform'"}, {"name": "ones", "value": "'ones'"}, {"name": "orthogonal", "value": "'orthogonal'"}, {"name": "random_normal", "value": "'random_normal'"}, {"name": "random_uniform", "value": "'random_uniform'"}, {"name": "serialize", "value": "'serialize'"}, {"name": "truncated_normal", "value": "'truncated_normal'"}, {"name": "variance_scaling", "value": "'variance_scaling'"}, {"name": "zeros", "value": "'zeros'"}]}, "bias_initializer": {"value": "zeros", "type": "list", "render": "list", "options": [{"name": "glorot_uniform", "value": "'glorot_uniform'"}, {"name": "glorot_normal", "value": "'glorot_normal'"}, {"name": "he_normal", "value": "'he_normal'"}, {"name": "he_uniform", "value": "'he_uniform'"}, {"name": "identity", "value": "'identity'"}, {"name": "lecun_normal", "value": "'lecun_normal'"}, {"name": "lecun_uniform", "value": "'lecun_uniform'"}, {"name": "ones", "value": "'ones'"}, {"name": "orthogonal", "value": "'orthogonal'"}, {"name": "random_normal", "value": "'random_normal'"}, {"name": "random_uniform", "value": "'random_uniform'"}, {"name": "serialize", "value": "'serialize'"}, {"name": "truncated_normal", "value": "'truncated_normal'"}, {"name": "variance_scaling", "value": "'variance_scaling'"}, {"name": "zeros", "value": "'zeros'"}]}}}, "conv2d_2": {"id": "conv2d_2", "name": "Conv2D 2", "type": "Conv2D", "pos": {"x": 363, "y": 274}, "connections": {"inbound": ["conv2d_1"], "outbound": ["conv2d_3"]}, "arguments": {"filters": {"value": "32", "type": "number", "render": "text"}, "kernel_size": {"value": "3", "type": "number", "render": "text"}, "strides": {"value": "2", "type": "number", "render": "text"}, "padding": {"value": "same", "type": "list", "render": "list", "options": [{"name": "valid", "value": "'valid'"}, {"name": "same", "value": "'same'"}]}, "activation": {"value": "relu", "type": "text", "render": "list", "options": [{"name": "None", "value": "None"}, {"name": "relu", "value": "\"relu\""}, {"name": "sigmoid", "value": "\"sigmoid\""}, {"name": "softmax", "value": "\"softmax\""}, {"name": "swish", "value": "\"swish\""}, {"name": "tanh", "value": "\"tanh\""}]}, "use_bias": {"value": "True", "type": "list", "render": "list", "options": [{"name": "True", "value": "True"}, {"name": "False", "value": "False"}]}, "kernel_initializer": {"value": "glorot_uniform", "type": "list", "render": "list", "options": [{"name": "glorot_uniform", "value": "'glorot_uniform'"}, {"name": "glorot_normal", "value": "'glorot_normal'"}, {"name": "he_normal", "value": "'he_normal'"}, {"name": "he_uniform", "value": "'he_uniform'"}, {"name": "identity", "value": "'identity'"}, {"name": "lecun_normal", "value": "'lecun_normal'"}, {"name": "lecun_uniform", "value": "'lecun_uniform'"}, {"name": "ones", "value": "'ones'"}, {"name": "orthogonal", "value": "'orthogonal'"}, {"name": "random_normal", "value": "'random_normal'"}, {"name": "random_uniform", "value": "'random_uniform'"}, {"name": "serialize", "value": "'serialize'"}, {"name": "truncated_normal", "value": "'truncated_normal'"}, {"name": "variance_scaling", "value": "'variance_scaling'"}, {"name": "zeros", "value": "'zeros'"}]}, "bias_initializer": {"value": "zeros", "type": "list", "render": "list", "options": [{"name": "glorot_uniform", "value": "'glorot_uniform'"}, {"name": "glorot_normal", "value": "'glorot_normal'"}, {"name": "he_normal", "value": "'he_normal'"}, {"name": "he_uniform", "value": "'he_uniform'"}, {"name": "identity", "value": "'identity'"}, {"name": "lecun_normal", "value": "'lecun_normal'"}, {"name": "lecun_uniform", "value": "'lecun_uniform'"}, {"name": "ones", "value": "'ones'"}, {"name": "orthogonal", "value": "'orthogonal'"}, {"name": "random_normal", "value": "'random_normal'"}, {"name": "random_uniform", "value": "'random_uniform'"}, {"name": "serialize", "value": "'serialize'"}, {"name": "truncated_normal", "value": "'truncated_normal'"}, {"name": "variance_scaling", "value": "'variance_scaling'"}, {"name": "zeros", "value": "'zeros'"}]}}}, "conv2d_3": {"id": "conv2d_3", "name": "Conv2D 3", "type": "Conv2D", "pos": {"x": 416, "y": 374}, "connections": {"inbound": ["conv2d_2"], "outbound": ["globalaveragepooling2d_1"]}, "arguments": {"filters": {"value": "32", "type": "number", "render": "text"}, "kernel_size": {"value": "3", "type": "number", "render": "text"}, "strides": {"value": "2", "type": "number", "render": "text"}, "padding": {"value": "same", "type": "list", "render": "list", "options": [{"name": "valid", "value": "'valid'"}, {"name": "same", "value": "'same'"}]}, "activation": {"value": "relu", "type": "text", "render": "list", "options": [{"name": "None", "value": "None"}, {"name": "relu", "value": "\"relu\""}, {"name": "sigmoid", "value": "\"sigmoid\""}, {"name": "softmax", "value": "\"softmax\""}, {"name": "swish", "value": "\"swish\""}, {"name": "tanh", "value": "\"tanh\""}]}, "use_bias": {"value": "True", "type": "list", "render": "list", "options": [{"name": "True", "value": "True"}, {"name": "False", "value": "False"}]}, "kernel_initializer": {"value": "glorot_uniform", "type": "list", "render": "list", "options": [{"name": "glorot_uniform", "value": "'glorot_uniform'"}, {"name": "glorot_normal", "value": "'glorot_normal'"}, {"name": "he_normal", "value": "'he_normal'"}, {"name": "he_uniform", "value": "'he_uniform'"}, {"name": "identity", "value": "'identity'"}, {"name": "lecun_normal", "value": "'lecun_normal'"}, {"name": "lecun_uniform", "value": "'lecun_uniform'"}, {"name": "ones", "value": "'ones'"}, {"name": "orthogonal", "value": "'orthogonal'"}, {"name": "random_normal", "value": "'random_normal'"}, {"name": "random_uniform", "value": "'random_uniform'"}, {"name": "serialize", "value": "'serialize'"}, {"name": "truncated_normal", "value": "'truncated_normal'"}, {"name": "variance_scaling", "value": "'variance_scaling'"}, {"name": "zeros", "value": "'zeros'"}]}, "bias_initializer": {"value": "zeros", "type": "list", "render": "list", "options": [{"name": "glorot_uniform", "value": "'glorot_uniform'"}, {"name": "glorot_normal", "value": "'glorot_normal'"}, {"name": "he_normal", "value": "'he_normal'"}, {"name": "he_uniform", "value": "'he_uniform'"}, {"name": "identity", "value": "'identity'"}, {"name": "lecun_normal", "value": "'lecun_normal'"}, {"name": "lecun_uniform", "value": "'lecun_uniform'"}, {"name": "ones", "value": "'ones'"}, {"name": "orthogonal", "value": "'orthogonal'"}, {"name": "random_normal", "value": "'random_normal'"}, {"name": "random_uniform", "value": "'random_uniform'"}, {"name": "serialize", "value": "'serialize'"}, {"name": "truncated_normal", "value": "'truncated_normal'"}, {"name": "variance_scaling", "value": "'variance_scaling'"}, {"name": "zeros", "value": "'zeros'"}]}}}, "globalaveragepooling2d_1": {"id": "globalaveragepooling2d_1", "name": "GlobalAveragePooling2D 1", "type": "GlobalAveragePooling2D", "pos": {"x": 439, "y": 490}, "connections": {"inbound": ["conv2d_3"], "outbound": ["dense_1"]}, "arguments": {}}, "dense_1": {"id": "dense_1", "name": "Dense 1", "type": "Dense", "pos": {"x": 491, "y": 592}, "connections": {"inbound": ["globalaveragepooling2d_1"], "outbound": ["model_1"]}, "arguments": {"units": {"value": "10", "type": "number", "render": "text"}, "activation": {"value": "softmax", "type": "text", "render": "list", "options": [{"name": "None", "value": "None"}, {"name": "relu", "value": "\"relu\""}, {"name": "sigmoid", "value": "\"sigmoid\""}, {"name": "softmax", "value": "\"softmax\""}, {"name": "swish", "value": "\"swish\""}, {"name": "tanh", "value": "\"tanh\""}]}, "use_bias": {"value": "False", "type": "list", "render": "list", "options": [{"name": "True", "value": "True"}, {"name": "False", "value": "False"}]}, "kernel_initializer": {"value": "glorot_uniform", "type": "list", "render": "list", "options": [{"name": "glorot_uniform", "value": "'glorot_uniform'"}, {"name": "glorot_normal", "value": "'glorot_normal'"}, {"name": "he_normal", "value": "'he_normal'"}, {"name": "he_uniform", "value": "'he_uniform'"}, {"name": "identity", "value": "'identity'"}, {"name": "lecun_normal", "value": "'lecun_normal'"}, {"name": "lecun_uniform", "value": "'lecun_uniform'"}, {"name": "ones", "value": "'ones'"}, {"name": "orthogonal", "value": "'orthogonal'"}, {"name": "random_normal", "value": "'random_normal'"}, {"name": "random_uniform", "value": "'random_uniform'"}, {"name": "serialize", "value": "'serialize'"}, {"name": "truncated_normal", "value": "'truncated_normal'"}, {"name": "variance_scaling", "value": "'variance_scaling'"}, {"name": "zeros", "value": "'zeros'"}]}, "bias_initializer": {"value": "zeros", "type": "list", "render": "list", "options": [{"name": "glorot_uniform", "value": "'glorot_uniform'"}, {"name": "glorot_normal", "value": "'glorot_normal'"}, {"name": "he_normal", "value": "'he_normal'"}, {"name": "he_uniform", "value": "'he_uniform'"}, {"name": "identity", "value": "'identity'"}, {"name": "lecun_normal", "value": "'lecun_normal'"}, {"name": "lecun_uniform", "value": "'lecun_uniform'"}, {"name": "ones", "value": "'ones'"}, {"name": "orthogonal", "value": "'orthogonal'"}, {"name": "random_normal", "value": "'random_normal'"}, {"name": "random_uniform", "value": "'random_uniform'"}, {"name": "serialize", "value": "'serialize'"}, {"name": "truncated_normal", "value": "'truncated_normal'"}, {"name": "variance_scaling", "value": "'variance_scaling'"}, {"name": "zeros", "value": "'zeros'"}]}}}, "model_1": {"id": "model_1", "name": "Model 1", "type": "Model", "pos": {"x": 519, "y": 686}, "connections": {"inbound": ["dense_1"], "outbound": ["compile_1"]}, "arguments": {}}, "compile_1": {"id": "compile_1", "name": "Compile 1", "type": "Compile", "pos": {"x": 561, "y": 758}, "connections": {"inbound": ["model_1"], "outbound": ["train_1"]}, "arguments": {"optmizer": {"value": "rmsprop", "type": "list", "render": "list", "options": [{"name": "adadelta", "value": "'adadelta'"}, {"name": "adagrad", "value": "'adagrad'"}, {"name": "adam", "value": "'adam'"}, {"name": "adamax", "value": "'adamax'"}, {"name": "ftrl", "value": "'ftrl'"}, {"name": "nadam", "value": "'nadam'"}, {"name": "optimizer", "value": "'optimizer'"}, {"name": "rmsprop", "value": "'rmsprop'"}, {"name": "sgd", "value": "'sgd'"}]}, "loss": {"value": "binary_crossentropy", "type": "list", "render": "list", "options": [{"name": "binary_crossentropy", "value": "'binary_crossentropy'"}, {"name": "categorical_crossentropy", "value": "'categorical_crossentropy'"}, {"name": "categorical_hinge", "value": "'categorical_hinge'"}, {"name": "cosine_similarity", "value": "'cosine_similarity'"}, {"name": "deserialize", "value": "'deserialize'"}, {"name": "get", "value": "'get'"}, {"name": "hinge", "value": "'hinge'"}, {"name": "huber", "value": "'huber'"}, {"name": "kl_divergence", "value": "'kl_divergence'"}, {"name": "kld", "value": "'kld'"}, {"name": "kullback_leibler_divergence", "value": "'kullback_leibler_divergence'"}, {"name": "log_cosh", "value": "'log_cosh'"}, {"name": "logcosh", "value": "'logcosh'"}, {"name": "mae", "value": "'mae'"}, {"name": "mape", "value": "'mape'"}, {"name": "mean_absolute_error", "value": "'mean_absolute_error'"}, {"name": "mean_absolute_percentage_error", "value": "'mean_absolute_percentage_error'"}, {"name": "mean_squared_error", "value": "'mean_squared_error'"}, {"name": "mean_squared_logarithmic_error", "value": "'mean_squared_logarithmic_error'"}, {"name": "mse", "value": "'mse'"}, {"name": "msle", "value": "'msle'"}, {"name": "poisson", "value": "'poisson'"}, {"name": "serialize", "value": "'serialize'"}, {"name": "sparse_categorical_crossentropy", "value": "'sparse_categorical_crossentropy'"}, {"name": "squared_hinge", "value": "'squared_hinge'"}]}}}, "train_1": {"id": "train_1", "name": "Train 1", "type": "Train", "pos": {"x": 636, "y": 832}, "connections": {"inbound": ["compile_1"], "outbound": []}, "arguments": {}}}